laser/__init__.py
laser/ethereum/__init__.py
laser/ethereum/gascost.py
laser/ethereum/helper.py
laser/ethereum/svm.py
laser/ethereum/taint_analysis.py
laser/ethereum/modules/__init__.py
laser_ethereum-0.17.11.dist-info/DESCRIPTION.rst
laser_ethereum-0.17.11.dist-info/METADATA
laser_ethereum-0.17.11.dist-info/RECORD
laser_ethereum-0.17.11.dist-info/WHEEL
laser_ethereum-0.17.11.dist-info/metadata.json
laser_ethereum-0.17.11.dist-info/top_level.txt
